LICENSE
README.md
setup.py
jabutiutils/JbtUtils.py
jabutiutils/__init__.py
jabutiutils.egg-info/PKG-INFO
jabutiutils.egg-info/SOURCES.txt
jabutiutils.egg-info/dependency_links.txt
jabutiutils.egg-info/requires.txt
jabutiutils.egg-info/top_level.txt
jabutiutils/ms_identity_web/__init__.py
jabutiutils/ms_identity_web/adapters.py
jabutiutils/ms_identity_web/configuration.py
jabutiutils/ms_identity_web/constants.py
jabutiutils/ms_identity_web/context.py
jabutiutils/ms_identity_web/errors.py
jabutiutils/ms_identity_web/django/__init__.py
jabutiutils/ms_identity_web/django/adapter.py
jabutiutils/ms_identity_web/django/middleware.py
jabutiutils/ms_identity_web/django/msal_views_and_urls.py